Workbook

Sheet Dashboard
A1: Gold Portfolio Valuation Dashboard
A2: Update the highlighted spot price on the Purity & Rates sheet, then enter each piece on the Item Calculator.
A4: Key Assumption | B4: Value | D4: Portfolio Value Scenarios
A5: Gold Spot Price ($/troy oz) | B5: ='Purity & Rates'!B4 -> 3434.37 | D5: Scenario | E5: Estimated Value | F5: 75% of Estimated Value
A6: Dealer Payout % | B6: ='Purity & Rates'!B5 -> 0.9 | D6: Full Melt Value | E6: =SUM('Item Calculator'!J5:J104) -> 9372.0765
A7: Pawn Payout % | B7: ='Purity & Rates'!B6 -> 0.75 | D7: Dealer Estimate | E7: =SUM('Item Calculator'!K5:K104) -> 8434.8688
A8: Items Entered | B8: =COUNTIF('Item Calculator'!B5:B104,"<>") -> 10 | D8: Pawn Estimate | E8: =SUM('Item Calculator'!L5:L104) -> 7029.0573
A9: Gross Weight (g) | B9: =SUM('Item Calculator'!D5:D104) -> 141.55 | D9: Gain/(Loss) at Melt | E9: =E6-B11 -> 9372.0765
A10: Pure Gold Weight (g) | B10: =SUM('Item Calculator'!I5:I104) -> 84.87856 | D10: Gain/(Loss) at Dealer | E10: =E7-B11 -> 8434.8688 | F10: =E10 * 0.75 -> 6326.1516
A11: Total Purchase Cost ($) | B11: =SUM('Item Calculator'!M5:M104) -> 0
A14: Karat Summary | B14: Item Count | C14: Net Gold Weight (g) | D14: Pure Gold (g) | E14: Melt Value ($) | F14: Dealer Estimate ($)
A15: 24K | B15: =COUNTIF('Item Calculator'!$C$5:$C$104,A15) -> 0 | C15: =SUMIF('Item Calculator'!$C$5:$C$104,A15,'Item Calculator'!$F$5:$F$104) -> 0 | D15: =SUMIF('Item Calculator'!$C$5:$C$104,A15,'Item Calculator'!$I$5:$I$104) -> 0 | E15: =SUMIF('Item Calculator'!$C$5:$C$104,A15,'Item Calculator'!$J$5:$J$104) -> 0 | F15: =SUMIF('Item Calculator'!$C$5:$C$104,A15,'Item Calculator'!$K$5:$K$104) -> 0
A16: 22K | B16: =COUNTIF('Item Calculator'!$C$5:$C$104,A16) -> 0 | C16: =SUMIF('Item Calculator'!$C$5:$C$104,A16,'Item Calculator'!$F$5:$F$104) -> 0 | D16: =SUMIF('Item Calculator'!$C$5:$C$104,A16,'Item Calculator'!$I$5:$I$104) -> 0 | E16: =SUMIF('Item Calculator'!$C$5:$C$104,A16,'Item Calculator'!$J$5:$J$104) -> 0 | F16: =SUMIF('Item Calculator'!$C$5:$C$104,A16,'Item Calculator'!$K$5:$K$104) -> 0
A17: 18K | B17: =COUNTIF('Item Calculator'!$C$5:$C$104,A17) -> 3 | C17: =SUMIF('Item Calculator'!$C$5:$C$104,A17,'Item Calculator'!$F$5:$F$104) -> 61.23 | D17: =SUMIF('Item Calculator'!$C$5:$C$104,A17,'Item Calculator'!$I$5:$I$104) -> 45.9225 | E17: =SUMIF('Item Calculator'!$C$5:$C$104,A17,'Item Calculator'!$J$5:$J$104) -> 5070.6466 | F17: =SUMIF('Item Calculator'!$C$5:$C$104,A17,'Item Calculator'!$K$5:$K$104) -> 4563.5819
A18: 14K | B18: =COUNTIF('Item Calculator'!$C$5:$C$104,A18) -> 7 | C18: =SUMIF('Item Calculator'!$C$5:$C$104,A18,'Item Calculator'!$F$5:$F$104) -> 66.82 | D18: =SUMIF('Item Calculator'!$C$5:$C$104,A18,'Item Calculator'!$I$5:$I$104) -> 38.95606 | E18: =SUMIF('Item Calculator'!$C$5:$C$104,A18,'Item Calculator'!$J$5:$J$104) -> 4301.4299 | F18: =SUMIF('Item Calculator'!$C$5:$C$104,A18,'Item Calculator'!$K$5:$K$104) -> 3871.2869
A19: 10K | B19: =COUNTIF('Item Calculator'!$C$5:$C$104,A19) -> 0 | C19: =SUMIF('Item Calculator'!$C$5:$C$104,A19,'Item Calculator'!$F$5:$F$104) -> 0 | D19: =SUMIF('Item Calculator'!$C$5:$C$104,A19,'Item Calculator'!$I$5:$I$104) -> 0 | E19: =SUMIF('Item Calculator'!$C$5:$C$104,A19,'Item Calculator'!$J$5:$J$104) -> 0 | F19: =SUMIF('Item Calculator'!$C$5:$C$104,A19,'Item Calculator'!$K$5:$K$104) -> 0
A20: Custom | B20: =COUNTIF('Item Calculator'!$C$5:$C$104,A20) -> 0 | C20: =SUMIF('Item Calculator'!$C$5:$C$104,A20,'Item Calculator'!$F$5:$F$104) -> 0 | D20: =SUMIF('Item Calculator'!$C$5:$C$104,A20,'Item Calculator'!$I$5:$I$104) -> 0 | E20: =SUMIF('Item Calculator'!$C$5:$C$104,A20,'Item Calculator'!$J$5:$J$104) -> 0 | F20: =SUMIF('Item Calculator'!$C$5:$C$104,A20,'Item Calculator'!$K$5:$K$104) -> 0
A23: How to Use This Model
A24: 1. | B24: Calibrate the pocket scale and set it to grams.
A25: 2. | B25: Identify the hallmark or tested karat. Use Custom only when entering a measured purity override.
A26: 3. | B26: Enter gross weight and deduct stones/non-gold parts. The workbook calculates net weight, pure-gold content, and values.
A27: 4. | B27: Enter what you paid for each piece to calculate investment gain/loss and ROI.
A28: 5. | B28: Treat full melt value as a theoretical ceiling before refining and transaction costs; dealer and pawn values are modeled estimates.
A29: 6. | B29: Update the spot price whenever you want a current valuation.

Sheet Item Calculator
A1: Gold Item Valuation Ledger
A2: Enter blue-font cells only. Keep different karats on separate rows. Use the non-gold deduction for stones, clasps, springs, or other components.
A4: Item # | B4: Description | C4: Karat | D4: Gross Weight (g) | E4: Non-Gold Deduction (g) | F4: Net Gold Weight (g) | G4: Purity Override % | H4: Applied Purity % | I4: Pure Gold (g) | J4: Melt Value ($) | K4: Dealer Est. 90% ($) | L4: Pawn Est. 75% ($) | M4: Purchase Cost ($) | N4: Gain/(Loss) at Melt ($) | O4: ROI at Melt | P4: Gain/(Loss) at Dealer ($) | Q4: Hallmark / Test Notes | R4: Status
A5: =ROW()-4 -> 1 | B5: Gold Bracelet (Twisted) | C5: 18K | D5: 27.22 | F5: =IF(D5="","",MAX(D5-IF(E5="",0,E5),0)) -> 27.22 | H5: =IF(G5<>"",G5,IFERROR(VLOOKUP(C5,'Purity & Rates'!$A$11:$B$16,2,FALSE),"")) -> 0.75 | I5: =IF(OR(F5="",H5=""),"",F5*H5) -> 20.415 | J5: =IF(I5="","",I5*'Purity & Rates'!$B$4/'Purity & Rates'!$B$7) -> 2254.1728 | K5: =IF(J5="","",J5*'Purity & Rates'!$B$5) -> 2028.7555 | L5: =IF(J5="","",J5*'Purity & Rates'!$B$6) -> 1690.6296 | N5: =IF(OR(J5="",M5=""),"",J5-M5) | O5: =IF(OR(N5="",M5=0),"",N5/M5) | P5: =IF(OR(K5="",M5=""),"",K5-M5)
A6: =ROW()-4 -> 2 | B6: Gold Bracelet (Link) | C6: 14K | D6: 21.59 | F6: =IF(D6="","",MAX(D6-IF(E6="",0,E6),0)) -> 21.59 | H6: =IF(G6<>"",G6,IFERROR(VLOOKUP(C6,'Purity & Rates'!$A$11:$B$16,2,FALSE),"")) -> 0.583 | I6: =IF(OR(F6="",H6=""),"",F6*H6) -> 12.58697 | J6: =IF(I6="","",I6*'Purity & Rates'!$B$4/'Purity & Rates'!$B$7) -> 1389.8215 | K6: =IF(J6="","",J6*'Purity & Rates'!$B$5) -> 1250.8393 | L6: =IF(J6="","",J6*'Purity & Rates'!$B$6) -> 1042.3661 | N6: =IF(OR(J6="",M6=""),"",J6-M6) | O6: =IF(OR(N6="",M6=0),"",N6/M6) | P6: =IF(OR(K6="",M6=""),"",K6-M6)
A7: =ROW()-4 -> 3 | B7: Gold Necklace (Smooth) | C7: 18K | D7: 16.48 | F7: =IF(D7="","",MAX(D7-IF(E7="",0,E7),0)) -> 16.48 | H7: =IF(G7<>"",G7,IFERROR(VLOOKUP(C7,'Purity & Rates'!$A$11:$B$16,2,FALSE),"")) -> 0.75 | I7: =IF(OR(F7="",H7=""),"",F7*H7) -> 12.36 | J7: =IF(I7="","",I7*'Purity & Rates'!$B$4/'Purity & Rates'!$B$7) -> 1364.76 | K7: =IF(J7="","",J7*'Purity & Rates'!$B$5) -> 1228.284 | L7: =IF(J7="","",J7*'Purity & Rates'!$B$6) -> 1023.57 | N7: =IF(OR(J7="",M7=""),"",J7-M7) | O7: =IF(OR(N7="",M7=0),"",N7/M7) | P7: =IF(OR(K7="",M7=""),"",K7-M7)
A8: =ROW()-4 -> 4 | B8: Gold Necklace (Braided) | C8: 14K | D8: 16.1 | F8: =IF(D8="","",MAX(D8-IF(E8="",0,E8),0)) -> 16.1 | H8: =IF(G8<>"",G8,IFERROR(VLOOKUP(C8,'Purity & Rates'!$A$11:$B$16,2,FALSE),"")) -> 0.583 | I8: =IF(OR(F8="",H8=""),"",F8*H8) -> 9.3863 | J8: =IF(I8="","",I8*'Purity & Rates'!$B$4/'Purity & Rates'!$B$7) -> 1036.4116 | K8: =IF(J8="","",J8*'Purity & Rates'!$B$5) -> 932.77041 | L8: =IF(J8="","",J8*'Purity & Rates'!$B$6) -> 777.30867 | N8: =IF(OR(J8="",M8=""),"",J8-M8) | O8: =IF(OR(N8="",M8=0),"",N8/M8) | P8: =IF(OR(K8="",M8=""),"",K8-M8)
A9: =ROW()-4 -> 5 | B9: Gold Necklace (TightLink) | C9: 18K | D9: 17.53 | F9: =IF(D9="","",MAX(D9-IF(E9="",0,E9),0)) -> 17.53 | H9: =IF(G9<>"",G9,IFERROR(VLOOKUP(C9,'Purity & Rates'!$A$11:$B$16,2,FALSE),"")) -> 0.75 | I9: =IF(OR(F9="",H9=""),"",F9*H9) -> 13.1475 | J9: =IF(I9="","",I9*'Purity & Rates'!$B$4/'Purity & Rates'!$B$7) -> 1451.7138 | K9: =IF(J9="","",J9*'Purity & Rates'!$B$5) -> 1306.5424 | L9: =IF(J9="","",J9*'Purity & Rates'!$B$6) -> 1088.7853 | N9: =IF(OR(J9="",M9=""),"",J9-M9) | O9: =IF(OR(N9="",M9=0),"",N9/M9) | P9: =IF(OR(K9="",M9=""),"",K9-M9)
A10: =ROW()-4 -> 6 | B10: Earrings (Twist) | C10: 14K | D10: 8.3 | F10: =IF(D10="","",MAX(D10-IF(E10="",0,E10),0)) -> 8.3 | H10: =IF(G10<>"",G10,IFERROR(VLOOKUP(C10,'Purity & Rates'!$A$11:$B$16,2,FALSE),"")) -> 0.583 | I10: =IF(OR(F10="",H10=""),"",F10*H10) -> 4.8389 | J10: =IF(I10="","",I10*'Purity & Rates'!$B$4/'Purity & Rates'!$B$7) -> 534.29913 | K10: =IF(J10="","",J10*'Purity & Rates'!$B$5) -> 480.86922 | L10: =IF(J10="","",J10*'Purity & Rates'!$B$6) -> 400.72435 | N10: =IF(OR(J10="",M10=""),"",J10-M10) | O10: =IF(OR(N10="",M10=0),"",N10/M10) | P10: =IF(OR(K10="",M10=""),"",K10-M10)
A11: =ROW()-4 -> 7 | B11: Ring (Moon) | C11: 14K | D11: 11.26 | E11: 3.5 | F11: =IF(D11="","",MAX(D11-IF(E11="",0,E11),0)) -> 7.76 | H11: =IF(G11<>"",G11,IFERROR(VLOOKUP(C11,'Purity & Rates'!$A$11:$B$16,2,FALSE),"")) -> 0.583 | I11: =IF(OR(F11="",H11=""),"",F11*H11) -> 4.52408 | J11: =IF(I11="","",I11*'Purity & Rates'!$B$4/'Purity & Rates'!$B$7) -> 499.5375 | K11: =IF(J11="","",J11*'Purity & Rates'!$B$5) -> 449.58375 | L11: =IF(J11="","",J11*'Purity & Rates'!$B$6) -> 374.65312 | N11: =IF(OR(J11="",M11=""),"",J11-M11) | O11: =IF(OR(N11="",M11=0),"",N11/M11) | P11: =IF(OR(K11="",M11=""),"",K11-M11)
A12: =ROW()-4 -> 8 | B12: Pendant | C12: 14K | D12: 3.77 | E12: 1.5 | F12: =IF(D12="","",MAX(D12-IF(E12="",0,E12),0)) -> 2.27 | H12: =IF(G12<>"",G12,IFERROR(VLOOKUP(C12,'Purity & Rates'!$A$11:$B$16,2,FALSE),"")) -> 0.583 | I12: =IF(OR(F12="",H12=""),"",F12*H12) -> 1.32341 | J12: =IF(I12="","",I12*'Purity & Rates'!$B$4/'Purity & Rates'!$B$7) -> 146.12759 | K12: =IF(J12="","",J12*'Purity & Rates'!$B$5) -> 131.51483 | L12: =IF(J12="","",J12*'Purity & Rates'!$B$6) -> 109.5957 | N12: =IF(OR(J12="",M12=""),"",J12-M12) | O12: =IF(OR(N12="",M12=0),"",N12/M12) | P12: =IF(OR(K12="",M12=""),"",K12-M12)
A13: =ROW()-4 -> 9 | B13: Ring (Ruby) | C13: 14K | D13: 9.3 | E13: 4 | F13: =IF(D13="","",MAX(D13-IF(E13="",0,E13),0)) -> 5.3 | H13: =IF(G13<>"",G13,IFERROR(VLOOKUP(C13,'Purity & Rates'!$A$11:$B$16,2,FALSE),"")) -> 0.583 | I13: =IF(OR(F13="",H13=""),"",F13*H13) -> 3.0899 | J13: =IF(I13="","",I13*'Purity & Rates'!$B$4/'Purity & Rates'!$B$7) -> 341.17896 | K13: =IF(J13="","",J13*'Purity & Rates'!$B$5) -> 307.06107 | L13: =IF(J13="","",J13*'Purity & Rates'!$B$6) -> 255.88422 | N13: =IF(OR(J13="",M13=""),"",J13-M13) | O13: =IF(OR(N13="",M13=0),"",N13/M13) | P13: =IF(OR(K13="",M13=""),"",K13-M13)
A14: =ROW()-4 -> 10 | B14: Ring (Blue Stone) | C14: 14K | D14: 10 | E14: 4.5 | F14: =IF(D14="","",MAX(D14-IF(E14="",0,E14),0)) -> 5.5 | H14: =IF(G14<>"",G14,IFERROR(VLOOKUP(C14,'Purity & Rates'!$A$11:$B$16,2,FALSE),"")) -> 0.583 | I14: =IF(OR(F14="",H14=""),"",F14*H14) -> 3.2065 | J14: =IF(I14="","",I14*'Purity & Rates'!$B$4/'Purity & Rates'!$B$7) -> 354.05364 | K14: =IF(J14="","",J14*'Purity & Rates'!$B$5) -> 318.64828 | L14: =IF(J14="","",J14*'Purity & Rates'!$B$6) -> 265.54023 | N14: =IF(OR(J14="",M14=""),"",J14-M14) | O14: =IF(OR(N14="",M14=0),"",N14/M14) | P14: =IF(OR(K14="",M14=""),"",K14-M14)
A15: =ROW()-4 -> 11 | F15: =IF(D15="","",MAX(D15-IF(E15="",0,E15),0)) | H15: =IF(G15<>"",G15,IFERROR(VLOOKUP(C15,'Purity & Rates'!$A$11:$B$16,2,FALSE),"")) | I15: =IF(OR(F15="",H15=""),"",F15*H15) | J15: =IF(I15="","",I15*'Purity & Rates'!$B$4/'Purity & Rates'!$B$7) | K15: =IF(J15="","",J15*'Purity & Rates'!$B$5) | L15: =IF(J15="","",J15*'Purity & Rates'!$B$6) | N15: =IF(OR(J15="",M15=""),"",J15-M15) | O15: =IF(OR(N15="",M15=0),"",N15/M15) | P15: =IF(OR(K15="",M15=""),"",K15-M15)
A16: =ROW()-4 -> 12 | F16: =IF(D16="","",MAX(D16-IF(E16="",0,E16),0)) | H16: =IF(G16<>"",G16,IFERROR(VLOOKUP(C16,'Purity & Rates'!$A$11:$B$16,2,FALSE),"")) | I16: =IF(OR(F16="",H16=""),"",F16*H16) | J16: =IF(I16="","",I16*'Purity & Rates'!$B$4/'Purity & Rates'!$B$7) | K16: =IF(J16="","",J16*'Purity & Rates'!$B$5) | L16: =IF(J16="","",J16*'Purity & Rates'!$B$6) | N16: =IF(OR(J16="",M16=""),"",J16-M16) | O16: =IF(OR(N16="",M16=0),"",N16/M16) | P16: =IF(OR(K16="",M16=""),"",K16-M16)
A17: =ROW()-4 -> 13 | F17: =IF(D17="","",MAX(D17-IF(E17="",0,E17),0)) | H17: =IF(G17<>"",G17,IFERROR(VLOOKUP(C17,'Purity & Rates'!$A$11:$B$16,2,FALSE),"")) | I17: =IF(OR(F17="",H17=""),"",F17*H17) | J17: =IF(I17="","",I17*'Purity & Rates'!$B$4/'Purity & Rates'!$B$7) | K17: =IF(J17="","",J17*'Purity & Rates'!$B$5) | L17: =IF(J17="","",J17*'Purity & Rates'!$B$6) | N17: =IF(OR(J17="",M17=""),"",J17-M17) | O17: =IF(OR(N17="",M17=0),"",N17/M17) | P17: =IF(OR(K17="",M17=""),"",K17-M17)
A18: =ROW()-4 -> 14 | F18: =IF(D18="","",MAX(D18-IF(E18="",0,E18),0)) | H18: =IF(G18<>"",G18,IFERROR(VLOOKUP(C18,'Purity & Rates'!$A$11:$B$16,2,FALSE),"")) | I18: =IF(OR(F18="",H18=""),"",F18*H18) | J18: =IF(I18="","",I18*'Purity & Rates'!$B$4/'Purity & Rates'!$B$7) | K18: =IF(J18="","",J18*'Purity & Rates'!$B$5) | L18: =IF(J18="","",J18*'Purity & Rates'!$B$6) | N18: =IF(OR(J18="",M18=""),"",J18-M18) | O18: =IF(OR(N18="",M18=0),"",N18/M18) | P18: =IF(OR(K18="",M18=""),"",K18-M18)
A19: =ROW()-4 -> 15 | F19: =IF(D19="","",MAX(D19-IF(E19="",0,E19),0)) | H19: =IF(G19<>"",G19,IFERROR(VLOOKUP(C19,'Purity & Rates'!$A$11:$B$16,2,FALSE),"")) | I19: =IF(OR(F19="",H19=""),"",F19*H19) | J19: =IF(I19="","",I19*'Purity & Rates'!$B$4/'Purity & Rates'!$B$7) | K19: =IF(J19="","",J19*'Purity & Rates'!$B$5) | L19: =IF(J19="","",J19*'Purity & Rates'!$B$6) | N19: =IF(OR(J19="",M19=""),"",J19-M19) | O19: =IF(OR(N19="",M19=0),"",N19/M19) | P19: =IF(OR(K19="",M19=""),"",K19-M19)
A20: =ROW()-4 -> 16 | F20: =IF(D20="","",MAX(D20-IF(E20="",0,E20),0)) | H20: =IF(G20<>"",G20,IFERROR(VLOOKUP(C20,'Purity & Rates'!$A$11:$B$16,2,FALSE),"")) | I20: =IF(OR(F20="",H20=""),"",F20*H20) | J20: =IF(I20="","",I20*'Purity & Rates'!$B$4/'Purity & Rates'!$B$7) | K20: =IF(J20="","",J20*'Purity & Rates'!$B$5) | L20: =IF(J20="","",J20*'Purity & Rates'!$B$6) | N20: =IF(OR(J20="",M20=""),"",J20-M20) | O20: =IF(OR(N20="",M20=0),"",N20/M20) | P20: =IF(OR(K20="",M20=""),"",K20-M20)
A21: =ROW()-4 -> 17 | F21: =IF(D21="","",MAX(D21-IF(E21="",0,E21),0)) | H21: =IF(G21<>"",G21,IFERROR(VLOOKUP(C21,'Purity & Rates'!$A$11:$B$16,2,FALSE),"")) | I21: =IF(OR(F21="",H21=""),"",F21*H21) | J21: =IF(I21="","",I21*'Purity & Rates'!$B$4/'Purity & Rates'!$B$7) | K21: =IF(J21="","",J21*'Purity & Rates'!$B$5) | L21: =IF(J21="","",J21*'Purity & Rates'!$B$6) | N21: =IF(OR(J21="",M21=""),"",J21-M21) | O21: =IF(OR(N21="",M21=0),"",N21/M21) | P21: =IF(OR(K21="",M21=""),"",K21-M21)
A22: =ROW()-4 -> 18 | F22: =IF(D22="","",MAX(D22-IF(E22="",0,E22),0)) | H22: =IF(G22<>"",G22,IFERROR(VLOOKUP(C22,'Purity & Rates'!$A$11:$B$16,2,FALSE),"")) | I22: =IF(OR(F22="",H22=""),"",F22*H22) | J22: =IF(I22="","",I22*'Purity & Rates'!$B$4/'Purity & Rates'!$B$7) | K22: =IF(J22="","",J22*'Purity & Rates'!$B$5) | L22: =IF(J22="","",J22*'Purity & Rates'!$B$6) | N22: =IF(OR(J22="",M22=""),"",J22-M22) | O22: =IF(OR(N22="",M22=0),"",N22/M22) | P22: =IF(OR(K22="",M22=""),"",K22-M22)
A23: =ROW()-4 -> 19 | F23: =IF(D23="","",MAX(D23-IF(E23="",0,E23),0)) | H23: =IF(G23<>"",G23,IFERROR(VLOOKUP(C23,'Purity & Rates'!$A$11:$B$16,2,FALSE),"")) | I23: =IF(OR(F23="",H23=""),"",F23*H23) | J23: =IF(I23="","",I23*'Purity & Rates'!$B$4/'Purity & Rates'!$B$7) | K23: =IF(J23="","",J23*'Purity & Rates'!$B$5) | L23: =IF(J23="","",J23*'Purity & Rates'!$B$6) | N23: =IF(OR(J23="",M23=""),"",J23-M23) | O23: =IF(OR(N23="",M23=0),"",N23/M23) | P23: =IF(OR(K23="",M23=""),"",K23-M23)
A24: =ROW()-4 -> 20 | F24: =IF(D24="","",MAX(D24-IF(E24="",0,E24),0)) | H24: =IF(G24<>"",G24,IFERROR(VLOOKUP(C24,'Purity & Rates'!$A$11:$B$16,2,FALSE),"")) | I24: =IF(OR(F24="",H24=""),"",F24*H24) | J24: =IF(I24="","",I24*'Purity & Rates'!$B$4/'Purity & Rates'!$B$7) | K24: =IF(J24="","",J24*'Purity & Rates'!$B$5) | L24: =IF(J24="","",J24*'Purity & Rates'!$B$6) | N24: =IF(OR(J24="",M24=""),"",J24-M24) | O24: =IF(OR(N24="",M24=0),"",N24/M24) | P24: =IF(OR(K24="",M24=""),"",K24-M24)
A25: =ROW()-4 -> 21 | F25: =IF(D25="","",MAX(D25-IF(E25="",0,E25),0)) | H25: =IF(G25<>"",G25,IFERROR(VLOOKUP(C25,'Purity & Rates'!$A$11:$B$16,2,FALSE),"")) | I25: =IF(OR(F25="",H25=""),"",F25*H25) | J25: =IF(I25="","",I25*'Purity & Rates'!$B$4/'Purity & Rates'!$B$7) | K25: =IF(J25="","",J25*'Purity & Rates'!$B$5) | L25: =IF(J25="","",J25*'Purity & Rates'!$B$6) | N25: =IF(OR(J25="",M25=""),"",J25-M25) | O25: =IF(OR(N25="",M25=0),"",N25/M25) | P25: =IF(OR(K25="",M25=""),"",K25-M25)
A26: =ROW()-4 -> 22 | F26: =IF(D26="","",MAX(D26-IF(E26="",0,E26),0)) | H26: =IF(G26<>"",G26,IFERROR(VLOOKUP(C26,'Purity & Rates'!$A$11:$B$16,2,FALSE),"")) | I26: =IF(OR(F26="",H26=""),"",F26*H26) | J26: =IF(I26="","",I26*'Purity & Rates'!$B$4/'Purity & Rates'!$B$7) | K26: =IF(J26="","",J26*'Purity & Rates'!$B$5) | L26: =IF(J26="","",J26*'Purity & Rates'!$B$6) | N26: =IF(OR(J26="",M26=""),"",J26-M26) | O26: =IF(OR(N26="",M26=0),"",N26/M26) | P26: =IF(OR(K26="",M26=""),"",K26-M26)
... A104: =ROW()-4 -> 100 | F104: =IF(D104="","",MAX(D104-IF(E104="",0,E104),0)) | H104: =IF(G104<>"",G104,IFERROR(VLOOKUP(C104,'Purity & Rates'!$A$11:$B$16,2,FALSE),"")) | I104: =IF(OR(F104="",H104=""),"",F104*H104) | J104: =IF(I104="","",I104*'Purity & Rates'!$B$4/'Purity & Rates'!$B$7) | K104: =IF(J104="","",J104*'Purity & Rates'!$B$5) | L104: =IF(J104="","",J104*'Purity & Rates'!$B$6) | N104: =IF(OR(J104="",M104=""),"",J104-M104) | O104: =IF(OR(N104="",M104=0),"",N104/M104) | P104: =IF(OR(K104="",M104=""),"",K104-M104)
A106: TOTALS | D106: =SUM(D5:D104) -> 141.55 | E106: =SUM(E5:E104) -> 13.5 | F106: =SUM(F5:F104) -> 128.05 | I106: =SUM(I5:I104) -> 84.87856 | J106: =SUM(J5:J104) -> 9372.0765 | K106: =SUM(K5:K104) -> 8434.8688 | L106: =SUM(L5:L104) -> 7029.0573 | M106: =SUM(M5:M104) -> 0 | N106: =SUM(N5:N104) -> 0 | O106: =IF(M106=0,"",N106/M106) | P106: =SUM(P5:P104) -> 0

Sheet Purity & Rates
A1: Gold Purity & Valuation Reference
A3: Reference Inputs | B3: Value
A4: Spot Price ($/troy oz) | B4: 3434.37
A5: Dealer Payout % | B5: 0.9
A6: Pawn Payout % | B6: 0.75
A7: Grams per Troy Ounce | B7: 31.1035
A8: Reference Date/Source | B8: User-provided printed valuation sheet
A10: Karat | B10: Purity % | C10: Common Hallmark | D10: Melt Value / g | E10: Dealer Est. / g | F10: Pawn Est. / g
A11: 24K | B11: 1 | C11: 999 / 999.9 | D11: =IF(B11="","",B11*$B$4/$B$7) -> 110.41748 | E11: =IF(D11="","",D11*$B$5) -> 99.375729 | F11: =IF(D11="","",D11*$B$6) -> 82.813108
A12: 22K | B12: 0.916 | C12: 916 | D12: =IF(B12="","",B12*$B$4/$B$7) -> 101.14241 | E12: =IF(D12="","",D12*$B$5) -> 91.028168 | F12: =IF(D12="","",D12*$B$6) -> 75.856807
A13: 18K | B13: 0.75 | C13: 750 | D13: =IF(B13="","",B13*$B$4/$B$7) -> 82.813108 | E13: =IF(D13="","",D13*$B$5) -> 74.531797 | F13: =IF(D13="","",D13*$B$6) -> 62.109831
A14: 14K | B14: 0.583 | C14: 583 / 585 | D14: =IF(B14="","",B14*$B$4/$B$7) -> 64.373389 | E14: =IF(D14="","",D14*$B$5) -> 57.93605 | F14: =IF(D14="","",D14*$B$6) -> 48.280042
A15: 10K | B15: 0.417 | C15: 416 / 417 | D15: =IF(B15="","",B15*$B$4/$B$7) -> 46.044088 | E15: =IF(D15="","",D15*$B$5) -> 41.439679 | F15: =IF(D15="","",D15*$B$6) -> 34.533066
A16: Custom | C16: Use purity override on Item Calculator | D16: =IF(B16="","",B16*$B$4/$B$7) | E16: =IF(D16="","",D16*$B$5) | F16: =IF(D16="","",D16*$B$6)
A18: Reference Formula
A19: Intrinsic melt value: | B19: Net gold-bearing weight (g) × purity × [spot price ÷ 31.1035]
A20: V = M × P × (S ÷ 31.1035)
A21: M | B21: Net gold-bearing mass in grams
A22: P | B22: Applied purity percentage
A23: S | B23: Gold spot price per troy ounce
A25: Important Deductions / Checks
A26: 1 | B26: Weigh stones, clasps, springs, watch movements, and non-gold components separately or estimate a deduction.
A27: 2 | B27: Sort items by hallmark/karat before weighing. Do not combine different purities in one row.
A28: 3 | B28: Gold-plated, gold-filled, rolled-gold, and vermeil pieces are not valued as solid-gold melt unless tested and separated.
A29: 4 | B29: A buyer's offer may be below modeled dealer or pawn estimates because of testing fees, refining costs, condition, resale value, or uncertainty.
A30: 5 | B30: Use a calibrated gram scale. Record weight to the scale's reliable precision.

Sheet Instructions
A1: Gold Valuation Method — Practical Guide
A3: Topic | B3: Guidance
A4: Scale | B4: Use grams, place the scale on a stable surface, calibrate it, and repeat the reading at least twice.
A5: Hallmarks | B5: Common solid-gold marks include 24K/999, 22K/916, 18K/750, 14K/585, and 10K/417.
A6: Purity Override | B6: Only use this field when an acid test, XRF test, or reliable assay gives a purity that differs from the hallmark.
A7: Stones & Parts | B7: Deduct estimated non-gold weight. For high-value pieces, professional stone removal or XRF testing may be worthwhile.
A8: Melt Value | B8: Theoretical intrinsic value of contained gold at the entered spot price before refining, shipping, testing, and transaction costs.
A9: Dealer Estimate | B9: Modeled at 90% of melt value, matching the reference sheet. Actual offers vary.
A10: Pawn Estimate | B10: Modeled at 75% of melt value, matching the reference sheet. Actual offers vary.
A11: Investment Tracking | B11: Enter purchase cost to calculate unrealized gain/loss. Keep receipts, photographs, test results, and identifying notes.
A12: Warning | B12: Do not value plated, filled, or vermeil items as solid gold without testing. A hallmark alone is not conclusive.
A14: Source / Assumption Notes
A15: Reference sheet | B15: Gold Purity Valuation Reference supplied by the user; baseline spot price $4,162.50/troy ounce.
A16: Dealer model | B16: 90% of calculated melt value.
A17: Pawn model | B17: 75% of calculated melt value.
A18: Dynamic use | B18: Because gold prices move continuously, replace the yellow spot-price input before making a current decision.
